grox/__init__.py
grox/cli.py
grox/config.py
grox/context.py
grox/factory.py
grox/factory_cache.py
grox/grox.py
grox/logger.py
grox/project.py
grox/state.py
grox/documents/__init__.py
grox/documents/retriever.py
grox/documents/schema.py
grox/documents/store.py
grox/templates/grox.yaml.j2
grox/templates/main.py.j2
grox-0.1.0.dist-info/licenses/LICENSE
grox-0.1.0.dist-info/METADATA
grox-0.1.0.dist-info/WHEEL
grox-0.1.0.dist-info/entry_points.txt
grox-0.1.0.dist-info/top_level.txt
grox-0.1.0.dist-info/RECORD
