Metadata-Version: 2.4
Name: grox
Version: 0.1.0
Summary: Async-ready context and logging manager for multi-tenant services
Author-email: Phragman <a@staphi.com>
License: MIT
Requires-Python: <3.14,>=3.11
License-File: LICENSE
Requires-Dist: pydantic<3,>=1.10.0
Requires-Dist: structlog>=23.1.0
Requires-Dist: python-json-logger>=2.0.0
Requires-Dist: pyyaml>=6.0
Requires-Dist: click>=8.0
Requires-Dist: jinja2
Requires-Dist: langfabric<0.2.0,>=0.1.8
Requires-Dist: seyaml<1.0,>=0.1.1
Requires-Dist: langgraph<0.5.0,>=0.4.10
Requires-Dist: langgraph-checkpoint-redis<0.0.9,>=0.0.8
Requires-Dist: langchain-redis<0.3.0,>=0.2.3
Requires-Dist: colorama<0.5.0,>=0.4.6
Provides-Extra: test
Requires-Dist: pytest; extra == "test"
Dynamic: license-file
